[
    {
        "company": "XOM",
        "accessionNumber": "0000034088-16-000065",
        "filingDate": "2016-02-24",
        "url": "https://www.sec.gov/Archives/edgar/data/34088/000003408816000065/0000034088-16-000065.txt"
    },
    {
        "company": "CVX",
        "accessionNumber": "0000093410-16-000049",
        "filingDate": "2016-02-25",
        "url": "https://www.sec.gov/Archives/edgar/data/93410/000009341016000049/0000093410-16-000049.txt"
    },
    {
        "company": "COP",
        "accessionNumber": "0001193125-16-472901",
        "filingDate": "2016-02-23",
        "url": "https://www.sec.gov/Archives/edgar/data/1163165/000119312516472901/0001193125-16-472901.txt"
    },
    {
        "company": "EOG",
        "accessionNumber": "0000821189-16-000054",
        "filingDate": "2016-02-25",
        "url": "https://www.sec.gov/Archives/edgar/data/821189/000082118916000054/0000821189-16-000054.txt"
    },
    {
        "company": "OXY",
        "accessionNumber": "0000797468-16-000017",
        "filingDate": "2016-02-26",
        "url": "https://www.sec.gov/Archives/edgar/data/797468/000079746816000017/0000797468-16-000017.txt"
    },
    {
        "company": "PSX",
        "accessionNumber": "0001534701-16-000119",
        "filingDate": "2016-02-19",
        "url": "https://www.sec.gov/Archives/edgar/data/1534701/000153470116000119/0001534701-16-000119.txt"
    },
    {
        "company": "MPC",
        "accessionNumber": "0001510295-16-000078",
        "filingDate": "2016-02-26",
        "url": "https://www.sec.gov/Archives/edgar/data/1510295/000151029516000078/0001510295-16-000078.txt"
    },
    {
        "company": "VLO",
        "accessionNumber": "0001035002-16-000069",
        "filingDate": "2016-02-25",
        "url": "https://www.sec.gov/Archives/edgar/data/1035002/000103500216000069/0001035002-16-000069.txt"
    },
    {
        "company": "HES",
        "accessionNumber": "0001564590-16-013433",
        "filingDate": "2016-02-26",
        "url": "https://www.sec.gov/Archives/edgar/data/4447/000156459016013433/0001564590-16-013433.txt"
    },
    {
        "company": "DVN",
        "accessionNumber": "0001193125-16-466687",
        "filingDate": "2016-02-17",
        "url": "https://www.sec.gov/Archives/edgar/data/1090012/000119312516466687/0001193125-16-466687.txt"
    },
    {
        "company": "KMI",
        "accessionNumber": "0001506307-16-000072",
        "filingDate": "2016-02-16",
        "url": "https://www.sec.gov/Archives/edgar/data/1506307/000150630716000072/0001506307-16-000072.txt"
    },
    {
        "company": "WMB",
        "accessionNumber": "0000107263-16-000021",
        "filingDate": "2016-02-26",
        "url": "https://www.sec.gov/Archives/edgar/data/107263/000010726316000021/0000107263-16-000021.txt"
    },
    {
        "company": "HAL",
        "accessionNumber": "0000045012-16-000272",
        "filingDate": "2016-02-05",
        "url": "https://www.sec.gov/Archives/edgar/data/45012/000004501216000272/0000045012-16-000272.txt"
    },
    {
        "company": "EXE",
        "accessionNumber": "0000895126-16-000395",
        "filingDate": "2016-02-25",
        "url": "https://www.sec.gov/Archives/edgar/data/895126/000089512616000395/0000895126-16-000395.txt"
    }
]